CHANGES.txt
README.txt
bootstrap.py
buildout.cfg
setup.py
src/zope/__init__.py
src/zope.app.undo.egg-info/PKG-INFO
src/zope.app.undo.egg-info/SOURCES.txt
src/zope.app.undo.egg-info/dependency_links.txt
src/zope.app.undo.egg-info/namespace_packages.txt
src/zope.app.undo.egg-info/not-zip-safe
src/zope.app.undo.egg-info/requires.txt
src/zope.app.undo.egg-info/top_level.txt
src/zope/app/__init__.py
src/zope/app/undo/SETUP.cfg
src/zope/app/undo/__init__.py
src/zope/app/undo/browser.py
src/zope/app/undo/configure.zcml
src/zope/app/undo/interfaces.py
src/zope/app/undo/undo-configure.zcml
src/zope/app/undo/undo_all.pt
src/zope/app/undo/undo_macros.pt
src/zope/app/undo/undo_more.pt
src/zope/app/undo/tests/__init__.py
src/zope/app/undo/tests/test_prefix.py
src/zope/app/undo/tests/test_undoview.py
src/zope/app/undo/tests/test_zodbundomanager.py